{"Key": "ChangeNoticeCO:dict",
"IsTable:bool": false,
"DisplayName": "ChangeNoticeCO",
"Items:dicts": [{"Name": "validFrom:string",
"Type": "string",
"Nullable:bool": false,
"DisplayName": "validFrom",
"ParentKey": "ChangeNoticeCO:dict",
"IsStatic:bool": false},{"Name": "status:string",
"Type": "string",
"Nullable:bool": false,
"DisplayName": "status",
"ParentKey": "ChangeNoticeCO:dict",
"IsStatic:bool": false},{"Name": "maturity:string",
"Type": "string",
"Nullable:bool": true,
"DisplayName": "maturity",
"ParentKey": "ChangeNoticeCO:dict",
"IsStatic:bool": false},{"Name": "priority:string",
"Type": "string",
"Nullable:bool": true,
"DisplayName": "priority",
"ParentKey": "ChangeNoticeCO:dict",
"IsStatic:bool": false},{"Key": "key:dict",
"IsTable:bool": false,
"DisplayName": "key",
"Items:dicts": [{"Name": "id:string",
"Type": "string",
"Nullable:bool": true,
"DisplayName": "id",
"ParentKey": "ChangeNoticeCO:dict->key:dict",
"IsStatic:bool": false},{"Name": "tempPLMId:string",
"Type": "string",
"Nullable:bool": true,
"DisplayName": "tempPLMId",
"ParentKey": "ChangeNoticeCO:dict->key:dict",
"IsStatic:bool": false},{"Name": "tempERPId:string",
"Type": "string",
"Nullable:bool": true,
"DisplayName": "tempERPId",
"ParentKey": "ChangeNoticeCO:dict->key:dict",
"IsStatic:bool": false},{"Name": "type:string",
"Type": "string",
"Nullable:bool": false,
"DisplayName": "type",
"ParentKey": "ChangeNoticeCO:dict->key:dict",
"IsStatic:bool": false},{"Name": "version:string",
"Type": "string",
"Nullable:bool": true,
"DisplayName": "version",
"ParentKey": "ChangeNoticeCO:dict->key:dict",
"IsStatic:bool": false}]},{"Key": "names:dicts",
"IsTable:bool": true,
"DisplayName": "names",
"Items:dicts": [{"Name": "language:string",
"Type": "string",
"Nullable:bool": false,
"DisplayName": "language",
"ParentKey": "ChangeNoticeCO:dict->names:dicts",
"IsStatic:bool": false},{"Name": "value:string",
"Type": "string",
"Nullable:bool": false,
"DisplayName": "value",
"ParentKey": "ChangeNoticeCO:dict->names:dicts",
"IsStatic:bool": false}]},{"Key": "descriptions:dicts",
"IsTable:bool": true,
"DisplayName": "descriptions",
"Items:dicts": [{"Name": "language:string",
"Type": "string",
"Nullable:bool": false,
"DisplayName": "language",
"ParentKey": "ChangeNoticeCO:dict->descriptions:dicts",
"IsStatic:bool": false},{"Name": "value:string",
"Type": "string",
"Nullable:bool": false,
"DisplayName": "value",
"ParentKey": "ChangeNoticeCO:dict->descriptions:dicts",
"IsStatic:bool": false}]},{"Key": "relatedProductVersions:dicts",
"IsTable:bool": true,
"DisplayName": "relatedProductVersions",
"Items:dicts": [{"Name": "RELATION_TYPE:string",
"Type": "string",
"Nullable:bool": false,
"DisplayName": "RELATION_TYPE",
"ParentKey": "ChangeNoticeCO:dict->relatedProductVersions:dicts",
"IsStatic:bool": false},{"Key": "key:dict",
"IsTable:bool": false,
"DisplayName": "key",
"Items:dicts": [{"Name": "id:string",
"Type": "string",
"Nullable:bool": true,
"DisplayName": "id",
"ParentKey": "ChangeNoticeCO:dict->relatedProductVersions:dicts->key:dict",
"IsStatic:bool": false},{"Name": "tempPLMId:string",
"Type": "string",
"Nullable:bool": true,
"DisplayName": "tempPLMId",
"ParentKey": "ChangeNoticeCO:dict->relatedProductVersions:dicts->key:dict",
"IsStatic:bool": false},{"Name": "tempERPId:string",
"Type": "string",
"Nullable:bool": true,
"DisplayName": "tempERPId",
"ParentKey": "ChangeNoticeCO:dict->relatedProductVersions:dicts->key:dict",
"IsStatic:bool": false},{"Name": "type:string",
"Type": "string",
"Nullable:bool": false,
"DisplayName": "type",
"ParentKey": "ChangeNoticeCO:dict->relatedProductVersions:dicts->key:dict",
"IsStatic:bool": false},{"Name": "version:string",
"Type": "string",
"Nullable:bool": true,
"DisplayName": "version",
"ParentKey": "ChangeNoticeCO:dict->relatedProductVersions:dicts->key:dict",
"IsStatic:bool": false}]}]},{"Key": "relatedDocumentVersions:dicts",
"IsTable:bool": true,
"DisplayName": "relatedDocumentVersions",
"Items:dicts": [{"Name": "RELATION_TYPE:string",
"Type": "string",
"Nullable:bool": false,
"DisplayName": "RELATION_TYPE",
"ParentKey": "ChangeNoticeCO:dict->relatedDocumentVersions:dicts",
"IsStatic:bool": false},{"Key": "key:dict",
"IsTable:bool": false,
"DisplayName": "key",
"Items:dicts": [{"Name": "id:string",
"Type": "string",
"Nullable:bool": true,
"DisplayName": "id",
"ParentKey": "ChangeNoticeCO:dict->relatedDocumentVersions:dicts->key:dict",
"IsStatic:bool": false},{"Name": "tempPLMId:string",
"Type": "string",
"Nullable:bool": true,
"DisplayName": "tempPLMId",
"ParentKey": "ChangeNoticeCO:dict->relatedDocumentVersions:dicts->key:dict",
"IsStatic:bool": false},{"Name": "tempERPId:string",
"Type": "string",
"Nullable:bool": true,
"DisplayName": "tempERPId",
"ParentKey": "ChangeNoticeCO:dict->relatedDocumentVersions:dicts->key:dict",
"IsStatic:bool": false},{"Name": "type:string",
"Type": "string",
"Nullable:bool": false,
"DisplayName": "type",
"ParentKey": "ChangeNoticeCO:dict->relatedDocumentVersions:dicts->key:dict",
"IsStatic:bool": false},{"Name": "version:string",
"Type": "string",
"Nullable:bool": true,
"DisplayName": "version",
"ParentKey": "ChangeNoticeCO:dict->relatedDocumentVersions:dicts->key:dict",
"IsStatic:bool": false}]}]},{"Key": "relatedStructureVersions:dicts",
"IsTable:bool": true,
"DisplayName": "relatedStructureVersions",
"Items:dicts": [{"Name": "RELATION_TYPE:string",
"Type": "string",
"Nullable:bool": false,
"DisplayName": "RELATION_TYPE",
"ParentKey": "ChangeNoticeCO:dict->relatedStructureVersions:dicts",
"IsStatic:bool": false},{"Key": "key:dict",
"IsTable:bool": false,
"DisplayName": "key",
"Items:dicts": [{"Name": "tempPLMId:string",
"Type": "string",
"Nullable:bool": false,
"DisplayName": "tempPLMId",
"ParentKey": "ChangeNoticeCO:dict->relatedStructureVersions:dicts->key:dict",
"IsStatic:bool": false},{"Name": "tempERPId:string",
"Type": "string",
"Nullable:bool": false,
"DisplayName": "tempERPId",
"ParentKey": "ChangeNoticeCO:dict->relatedStructureVersions:dicts->key:dict",
"IsStatic:bool": false},{"Name": "type:string",
"Type": "string",
"Nullable:bool": false,
"DisplayName": "type",
"ParentKey": "ChangeNoticeCO:dict->relatedStructureVersions:dicts->key:dict",
"IsStatic:bool": false},{"Name": "alternative:string",
"Type": "string",
"Nullable:bool": false,
"DisplayName": "alternative",
"ParentKey": "ChangeNoticeCO:dict->relatedStructureVersions:dicts->key:dict",
"IsStatic:bool": false},{"Key": "productVersionKey:dict",
"IsTable:bool": false,
"DisplayName": "productVersionKey",
"Items:dicts": [{"Name": "id:string",
"Type": "string",
"Nullable:bool": true,
"DisplayName": "id",
"ParentKey": "ChangeNoticeCO:dict->relatedStructureVersions:dicts->key:dict->productVersionKey:dict",
"IsStatic:bool": false},{"Name": "tempPLMId:string",
"Type": "string",
"Nullable:bool": true,
"DisplayName": "tempPLMId",
"ParentKey": "ChangeNoticeCO:dict->relatedStructureVersions:dicts->key:dict->productVersionKey:dict",
"IsStatic:bool": false},{"Name": "tempERPId:string",
"Type": "string",
"Nullable:bool": true,
"DisplayName": "tempERPId",
"ParentKey": "ChangeNoticeCO:dict->relatedStructureVersions:dicts->key:dict->productVersionKey:dict",
"IsStatic:bool": false},{"Name": "type:string",
"Type": "string",
"Nullable:bool": false,
"DisplayName": "type",
"ParentKey": "ChangeNoticeCO:dict->relatedStructureVersions:dicts->key:dict->productVersionKey:dict",
"IsStatic:bool": false},{"Name": "version:string",
"Type": "string",
"Nullable:bool": true,
"DisplayName": "version",
"ParentKey": "ChangeNoticeCO:dict->relatedStructureVersions:dicts->key:dict->productVersionKey:dict",
"IsStatic:bool": false}]},{"Key": "factoryKey:dict",
"IsTable:bool": false,
"DisplayName": "factoryKey",
"Items:dicts": [{"Name": "id:string",
"Type": "string",
"Nullable:bool": false,
"DisplayName": "id",
"ParentKey": "ChangeNoticeCO:dict->relatedStructureVersions:dicts->key:dict->factoryKey:dict",
"IsStatic:bool": false},{"Name": "type:string",
"Type": "string",
"Nullable:bool": false,
"DisplayName": "type",
"ParentKey": "ChangeNoticeCO:dict->relatedStructureVersions:dicts->key:dict->factoryKey:dict",
"IsStatic:bool": false}]}]}]},{"Key": "extensionFields:dicts",
"IsTable:bool": true,
"DisplayName": "extensionFields",
"Items:dicts": [{"Name": "key:string",
"Type": "string",
"Nullable:bool": false,
"DisplayName": "key",
"ParentKey": "ChangeNoticeCO:dict->extensionFields:dicts",
"IsStatic:bool": false},{"Name": "subKey:string",
"Type": "string",
"Nullable:bool": true,
"DisplayName": "subKey",
"ParentKey": "ChangeNoticeCO:dict->extensionFields:dicts",
"IsStatic:bool": false},{"Name": "displayName:string",
"Type": "string",
"Nullable:bool": true,
"DisplayName": "displayName",
"ParentKey": "ChangeNoticeCO:dict->extensionFields:dicts",
"IsStatic:bool": false},{"Name": "value:string",
"Type": "string",
"Nullable:bool": true,
"DisplayName": "value",
"ParentKey": "ChangeNoticeCO:dict->extensionFields:dicts",
"IsStatic:bool": false},{"Name": "valueDescription:string",
"Type": "string",
"Nullable:bool": true,
"DisplayName": "valueDescription",
"ParentKey": "ChangeNoticeCO:dict->extensionFields:dicts",
"IsStatic:bool": false},{"Name": "valueInt:num",
"Type": "num",
"Nullable:bool": true,
"DisplayName": "valueInt",
"ParentKey": "ChangeNoticeCO:dict->extensionFields:dicts",
"IsStatic:bool": false},{"Name": "valueDec:num",
"Type": "num",
"Nullable:bool": true,
"DisplayName": "valueDec",
"ParentKey": "ChangeNoticeCO:dict->extensionFields:dicts",
"IsStatic:bool": false},{"Name": "valueDate:string",
"Type": "string",
"Nullable:bool": true,
"DisplayName": "valueDate",
"ParentKey": "ChangeNoticeCO:dict->extensionFields:dicts",
"IsStatic:bool": false},{"Name": "valueDuration:string",
"Type": "string",
"Nullable:bool": true,
"DisplayName": "valueDuration",
"ParentKey": "ChangeNoticeCO:dict->extensionFields:dicts",
"IsStatic:bool": false}]}],
"GenerationParameters": {"-EDMXFILEPATH": "C:\\Users\\infodba\\Desktop\\MetaDomainModel_supersprint_07_PR_CR_CN.edmx",
"+language": "en"}}
